CITATION
LICENSE
MANIFEST.in
README.rst
requirements.txt
setup.cfg
setup.py
bin/_preamble.py
bin/tnseqy
doc/Makefile
doc/changes.rst
doc/colorspace.rst
doc/conf.py
doc/guide.rst
doc/ideas.rst
doc/index.rst
doc/installation.rst
doc/recipes.rst
tnseq_yeast/__init__.py
tnseq_yeast/analyzeEssentiality.py
tnseq_yeast/analyzeEssentiality2.py
tnseq_yeast/buildLogisticRegressionModel.py
tnseq_yeast/compareLibraries.py
tnseq_yeast/log.py
tnseq_yeast/parseTnseqRawdata.py
tnseq_yeast/prepareMaterial.py
tnseq_yeast/preprocess.py
tnseq_yeast/scanGenomeInsertions.py
tnseq_yeast/scanGenomeInsertions2.py
tnseq_yeast/scanGenomeInsertions3.py
tnseq_yeast/visualization2.py
tnseq_yeast.egg-info/PKG-INFO
tnseq_yeast.egg-info/SOURCES.txt
tnseq_yeast.egg-info/dependency_links.txt
tnseq_yeast.egg-info/requires.txt
tnseq_yeast.egg-info/top_level.txt