Metadata-Version: 1.1
Name: tnseq-yeast
Version: 0.5.1
Summary: trim adapters from high-throughput sequencing reads
Home-page: https://tnseq_yeast.readthedocs.io/
Author: Jim Chu
Author-email: biojxz@163.com
License: MIT
Platform: UNKNOWN
Classifier: Development Status :: 5 - Production/Stable
Classifier: Environment :: Console
Classifier: Intended Audience :: Science/Research
Classifier: License :: OSI Approved :: MIT License
Classifier: Natural Language :: English
Classifier: Programming Language :: Cython
Classifier: Programming Language :: Python :: 2.7
Classifier: Programming Language :: Python :: 3
Classifier: Topic :: Scientific/Engineering :: Bio-Informatics
